carlae/__init__.py
carlae/cli/__init__.py
carlae/cli/__main__.py
carlae/cli/_version.py
carlae/client/__init__.py
carlae/client/__main__.py
carlae/client/cli.py
carlae/client/upload.py
carlae.cli-0.0.4.dist-info/LICENSE
carlae.cli-0.0.4.dist-info/METADATA
carlae.cli-0.0.4.dist-info/WHEEL
carlae.cli-0.0.4.dist-info/entry_points.txt
carlae.cli-0.0.4.dist-info/top_level.txt
carlae.cli-0.0.4.dist-info/RECORD
