Metadata-Version: 2.1
Name: carlae.cli
Version: 0.0.4
Summary: Carlae's CLI
Home-page: https://github.com/zeroae/carlae-cli
Author: Patrick Sodré
Author-email: psodre@gmail.com
License: MIT
Keywords: cli carlae
Platform: UNKNOWN
Classifier: Development Status :: 2 - Pre-Alpha
Classifier: Intended Audience :: Developers
Classifier: License :: OSI Approved :: MIT License
Classifier: Natural Language :: English
Classifier: Programming Language :: Python :: 3
Classifier: Programming Language :: Python :: 3.6
Classifier: Programming Language :: Python :: 3.7
Classifier: Programming Language :: Python :: 3.8
Requires-Python: >=3.6
Requires-Dist: click (>=7.0)
Requires-Dist: click-plugins
Requires-Dist: click-log
Requires-Dist: click-params
Requires-Dist: entrypoints
Provides-Extra: doc
Requires-Dist: sphinx ; extra == 'doc'
Requires-Dist: sphinx-autoapi ; extra == 'doc'
Requires-Dist: sphinx-click ; extra == 'doc'
Requires-Dist: watchdog ; extra == 'doc'
Provides-Extra: test
Requires-Dist: pytest (>=3) ; extra == 'test'
Requires-Dist: pytest-cov ; extra == 'test'
